{"coord":{"lon":-75.16,"lat":39.95},"weather":[{"id":500,"main":"Rain","description":"light rain","icon":"10n"},{"id":701,"main":"Mist","description":"mist","icon":"50n"},{"id":600,"main":"Snow","description":"light snow","icon":"13n"}],"base":"stations","main":{"temp":275.73,"pressure":995,"humidity":93,"temp_min":274.15,"temp_max":277.15},"visibility":9656,"wind":{"speed":6.7,"deg":350},"clouds":{"all":90},"dt":1485249300,"sys":{"type":1,"id":2359,"message":0.2159,"country":"US","sunrise":1485260104,"sunset":1485295872},"id":4560349,"name":"Philadelphia","cod":200}