{"coord":{"lon":-75.16,"lat":39.95},"weather":[{"id":501,"main":"Rain","description":"moderate rain","icon":"10d"},{"id":701,"main":"Mist","description":"mist","icon":"50d"}],"base":"cmc stations","main":{"temp":294.8,"pressure":1016,"humidity":88,"temp_min":293.15,"temp_max":296.48},"wind":{"speed":3.1,"deg":10},"rain":{"1h":1.65},"clouds":{"all":90},"dt":1436444403,"sys":{"type":1,"id":2359,"message":0.0056,"country":"US","sunrise":1436434829,"sunset":1436488264},"id":4560349,"name":"Philadelphia","cod":200}
