{"coord":{"lon":-75.16,"lat":39.95},"weather":[{"id":500,"main":"Rain","description":"light rain","icon":"10n"},{"id":701,"main":"Mist","description":"mist","icon":"50n"}],"base":"stations","main":{"temp":289.05,"pressure":992,"humidity":77,"temp_min":287.15,"temp_max":291.15},"visibility":16093,"wind":{"speed":9.3,"deg":190,"gust":11.8},"clouds":{"all":75},"dt":1456373820,"sys":{"type":1,"id":2359,"message":0.0491,"country":"US","sunrise":1456400413,"sunset":1456440466},"id":4560349,"name":"Philadelphia","cod":200}