{"coord":{"lon":-75.16,"lat":39.95},"weather":[{"id":501,"main":"Rain","description":"moderate rain","icon":"10d"},{"id":701,"main":"Mist","description":"mist","icon":"50d"}],"base":"cmc stations","main":{"temp":297.72,"pressure":1015,"humidity":69,"temp_min":295.93,"temp_max":301.15},"wind":{"speed":5.7,"deg":190},"rain":{"1h":3.48},"clouds":{"all":90},"dt":1469913497,"sys":{"type":1,"id":2359,"message":0.0047,"country":"US","sunrise":1469872715,"sunset":1469924090},"id":4560349,"name":"Philadelphia","cod":200}